taskgit.py
taskgit-0.1.dist-info/METADATA
taskgit-0.1.dist-info/WHEEL
taskgit-0.1.dist-info/entry_points.txt
taskgit-0.1.dist-info/top_level.txt
taskgit-0.1.dist-info/RECORD
