Metadata-Version: 2.4
Name: taskgit
Version: 0.1
Summary: Herramienta de gestión de tareas en la terminal con historial usando Git
Home-page: https://github.com/JoXBar/taskgit
Author: JoXBar
Author-email: 23josue.barrios@gmail.com
Classifier: Programming Language :: Python :: 3
Classifier: License :: OSI Approved :: MIT License
Classifier: Operating System :: OS Independent
Requires-Python: >=3.6
Dynamic: author
Dynamic: author-email
Dynamic: classifier
Dynamic: description
Dynamic: description-content-type
Dynamic: home-page
Dynamic: requires-python
Dynamic: summary
